yalexs/__init__.py
yalexs/_compat.py
yalexs/activity.py
yalexs/alarm.py
yalexs/api_async.py
yalexs/api_common.py
yalexs/authenticator_async.py
yalexs/authenticator_common.py
yalexs/backports/__init__.py
yalexs/backports/enum.py
yalexs/backports/tasks.py
yalexs/bridge.py
yalexs/capabilities.py
yalexs/const.py
yalexs/device.py
yalexs/doorbell.py
yalexs/exceptions.py
yalexs/keypad.py
yalexs/lock.py
yalexs/manager/__init__.py
yalexs/manager/activity.py
yalexs/manager/const.py
yalexs/manager/data.py
yalexs/manager/exceptions.py
yalexs/manager/gateway.py
yalexs/manager/ratelimit.py
yalexs/manager/socketio.py
yalexs/manager/subscriber.py
yalexs/pin.py
yalexs/pubnub_activity.py
yalexs/pubnub_async.py
yalexs/time.py
yalexs/users.py
yalexs/util.py
yalexs-9.2.0.dist-info/METADATA
yalexs-9.2.0.dist-info/WHEEL
yalexs-9.2.0.dist-info/licenses/LICENSE
yalexs-9.2.0.dist-info/RECORD
