Metadata-Version: 2.4
Name: yalexs
Version: 9.2.0
Summary: Python API for Yale Access (formerly August) Smart Lock and Doorbell
License: MIT
License-File: LICENSE
Author: J. Nick Koston
Author-email: nick@koston.org
Requires-Python: >=3.10,<4.0
Classifier: Development Status :: 5 - Production/Stable
Classifier: Intended Audience :: Developers
Classifier: License :: OSI Approved :: MIT License
Classifier: Natural Language :: English
Classifier: Operating System :: OS Independent
Classifier: Programming Language :: Python :: 3
Classifier: Programming Language :: Python :: 3.10
Classifier: Programming Language :: Python :: 3.11
Classifier: Programming Language :: Python :: 3.12
Classifier: Programming Language :: Python :: 3.13
Classifier: Programming Language :: Python :: 3.14
Classifier: Topic :: Software Development :: Libraries
Requires-Dist: aiofiles (>=23)
Requires-Dist: aiohttp (>=3.10.5)
Requires-Dist: ciso8601 (>=2.1.3)
Requires-Dist: freenub (>=0.1.0)
Requires-Dist: propcache (>=0.0.0)
Requires-Dist: pyjwt (>=2.8.0)
Requires-Dist: python-dateutil (>=2.9.0)
Requires-Dist: python-socketio[asyncio-client] (>=5.11.3)
Requires-Dist: requests (>=2)
Requires-Dist: typing-extensions (>=4.5.0)
Project-URL: Bug Tracker, https://github.com/bdraco/yalexs/issues
Project-URL: Changelog, https://github.com/bdraco/yalexs/blob/main/CHANGELOG.md
Project-URL: Documentation, https://yalexs.readthedocs.io
Project-URL: Repository, https://github.com/bdraco/yalexs
